stapler/__init__.py
stapler/homog.py
stapler/native_disulfide_stapler.py
stapler/stapler.py
stapler/hash_tables/default_native_disulfide.bin
pystapler-1.1.0.dist-info/METADATA
pystapler-1.1.0.dist-info/WHEEL
pystapler-1.1.0.dist-info/top_level.txt
pystapler-1.1.0.dist-info/RECORD
