Metadata-Version: 2.1
Name: pystapler
Version: 1.1.0
Summary: A Motif Hash Based Method for Matching Staples/Crosslinks into Peptides and Proteins
Home-page: https://github.com/atom-moyer/stapler
Author: Adam Moyer
Author-email: atom.moyer@gmail.com
License: UNKNOWN
Platform: UNKNOWN
Classifier: Programming Language :: Python :: 3
Classifier: Programming Language :: C++
Classifier: Topic :: Scientific/Engineering
Classifier: Topic :: Software Development
Classifier: License :: OSI Approved :: MIT License
Classifier: Operating System :: Unix
Requires-Dist: pyrosetta
Requires-Dist: xbin
Requires-Dist: numpy
Requires-Dist: getpy
